{
	"auto_trigger": false,
	"cutscene_id": "church_intro",
	"description": "Auto-generated cutscene",
	"dialog_file": "father_matthew",
	"dialog_title": "sermon_start",
	"location": "church_interior",
	"marker_positions": {
		"FM0": {
			"x": 594.0,
			"y": 235.0
		},
		"FM2": {
			"x": 1433.0,
			"y": 144.0
		},
		"IM0": {
			"x": 1000.0,
			"y": 238.0
		},
		"IM1": {
			"x": 840.0,
			"y": 238.0
		},
		"IM2": {
			"x": 1537.0,
			"y": 238.0
		},
		"A0": {
			"x": 222.0,
			"y": 506.0
		},
		"B0": {
			"x": 158.0,
			"y": 519.0
		},
		"I0": {
			"x": 94.0,
			"y": 519.0
		},
		"GA0": {
			"x": 535.0,
			"y": 125.0
		},
		"GA1": {
			"x": 530.0,
			"y": 230.0
		},
		"GA2": {
			"x": 1433.0,
			"y": 64.0
		},
		"SW0": {
			"x": 1433.0,
			"y": 224
		},
		"IM3": {
			"x": 850.0,
			"y": 350.0
		},
		"GA3": {
			"x": 924.0,
			"y": 350.0
		},
		"IM4": {
			"x": 606.0,
			"y": 401.0
		},
		"GA4": {
			"x": 680.0,
			"y": 401.0
		},
		"SW1": {
			"x": 586.0,
			"y": 442.0
		},
		"AZ0": {
			"x": 640.0,
			"y": 442.0
		},
		"GB0": {
			"x": 650.0,
			"y": 150.0
		},
		"GB1": {
			"x": 645.0,
			"y": 230.0
		},
		"GB2": {
			"x": 1433.0,
			"y": 224
		}
	},
	"npcs": [
	],
	"one_time": true,
	"priority": 1.0,
	"props": [],
	"triggers": [],
	"unlocks": []
}
