{
  "exportTimestamp": "2026-04-14T04-19-22",
  "bodyType": "female",
  "standardAnimations": {
    "exported": [
      "spellcast",
      "thrust",
      "walk",
      "slash",
      "shoot",
      "hurt",
      "climb",
      "idle",
      "jump",
      "sit",
      "emote",
      "run",
      "watering",
      "combat",
      "1h_slash",
      "1h_backslash",
      "1h_halfslash"
    ],
    "failed": []
  },
  "customAnimations": {
    "exported": [],
    "failed": []
  },
  "frameSize": 64,
  "frameCounts": {},
  "performance": {
    "exportKind": "splitAnimations",
    "totalMs": 402.7,
    "phasesMs": {
      "render_composite_extractAnimationFromCanvas": 2.9,
      "drawAndSlice": 7.8,
      "pngEncode": 354.3,
      "zipFile": 4.8,
      "staticFiles": 1
    },
    "counters": {
      "pngEncodeCount": 17,
      "totalPngBytes": 430305,
      "drawAndSliceCount": 17,
      "zipFileEntryCount": 17,
      "renderExtractAnimationFromCanvasCalls": 17,
      "renderSingleItemCalls": 0,
      "renderSingleItemAnimationCalls": 0,
      "extractFramesFromAnimationBatchCount": 0,
      "renderSliceCanvasForCustomAnimCalls": 0
    },
    "userAgent": "Mozilla/5.0 (Windows NT 10.0; Win64; x64) AppleWebKit/537.36 (KHTML, like Gecko) Chrome/146.0.0.0 Safari/537.36"
  }
}