{
  "version": 2,
  "bodyType": "male",
  "selections": {
    "body": {
      "itemId": "body",
      "subId": null,
      "variant": "",
      "recolor": "olive",
      "name": "Body Color (olive)"
    },
    "head": {
      "itemId": "heads_human_male",
      "subId": null,
      "variant": "",
      "recolor": "olive",
      "name": "Human Male (olive)"
    },
    "expression": {
      "itemId": "face_neutral",
      "subId": null,
      "variant": "",
      "recolor": "olive",
      "name": "Neutral (olive)"
    },
    "hair": {
      "itemId": "hair_afro",
      "subId": null,
      "variant": "light brown",
      "recolor": "",
      "name": "Afro (light brown)"
    },
    "jacket_collar": {
      "itemId": "torso_jacket_frock_collar",
      "subId": null,
      "variant": "gold",
      "recolor": "",
      "name": "Frock collar (gold)"
    },
    "clothes": {
      "itemId": "torso_clothes_longsleeve2_cardigan",
      "subId": null,
      "variant": "",
      "recolor": "green",
      "name": "Cardigan (green)"
    },
    "legs": {
      "itemId": "legs_pantaloons",
      "subId": null,
      "variant": "",
      "recolor": "green",
      "name": "Pantaloons (green)"
    },
    "shoes": {
      "itemId": "feet_sandals",
      "subId": null,
      "variant": "yellow",
      "recolor": "",
      "name": "Sandals (yellow)"
    }
  },
  "selectedAnimation": "idle",
  "showTransparencyGrid": true,
  "applyTransparencyMask": false,
  "matchBodyColorEnabled": true,
  "compactDisplay": false,
  "enabledLicenses": {
    "CC0": true,
    "CC-BY-SA": true,
    "CC-BY": true,
    "OGA-BY": true,
    "GPL": true
  },
  "enabledAnimations": {
    "spellcast": false,
    "thrust": false,
    "walk": false,
    "slash": false,
    "shoot": false,
    "hurt": false,
    "climb": false,
    "idle": false,
    "jump": false,
    "sit": false,
    "emote": false,
    "run": false,
    "watering": false,
    "combat": false,
    "1h_slash": false,
    "1h_backslash": false,
    "1h_halfslash": false
  },
  "url": "https://liberatedpixelcup.github.io/Universal-LPC-Spritesheet-Character-Generator/#sex=male&body=Body_Color_olive&head=Human_Male_olive&expression=Neutral_olive&hair=Afro_light%20brown&jacket_collar=Frock_collar_gold&clothes=Cardigan_green&legs=Pantaloons_green&shoes=Sandals_yellow",
  "layers": [
    {
      "itemId": "body",
      "name": "Body Color (olive)",
      "variant": "",
      "recolors": {
        "body": "olive"
      },
      "zPos": 10,
      "layerNum": 1,
      "yPos": 0,
      "isCustom": false,
      "needsRecolor": false,
      "fileName": "body/bodies/male/spellcast.png",
      "supportedAnimations": [
        "spellcast",
        "thrust",
        "walk",
        "slash",
        "shoot",
        "hurt",
        "climb",
        "idle",
        "jump",
        "sit",
        "emote",
        "run",
        "combat_idle",
        "backslash",
        "halfslash"
      ]
    },
    {
      "itemId": "feet_sandals",
      "name": "Sandals (yellow)",
      "variant": "yellow",
      "recolors": null,
      "zPos": 15,
      "layerNum": 1,
      "yPos": 0,
      "isCustom": false,
      "needsRecolor": false,
      "fileName": "feet/sandals/male/spellcast/yellow.png",
      "supportedAnimations": [
        "spellcast",
        "thrust",
        "walk",
        "slash",
        "shoot",
        "hurt",
        "climb",
        "idle",
        "jump",
        "sit",
        "emote",
        "run",
        "combat_idle",
        "backslash",
        "halfslash"
      ]
    },
    {
      "itemId": "legs_pantaloons",
      "name": "Pantaloons (green)",
      "variant": "",
      "recolors": {
        "legs": "green"
      },
      "zPos": 20,
      "layerNum": 1,
      "yPos": 0,
      "isCustom": false,
      "needsRecolor": false,
      "fileName": "legs/pantaloons/male/spellcast.png",
      "supportedAnimations": [
        "spellcast",
        "thrust",
        "walk",
        "slash",
        "shoot",
        "hurt",
        "climb",
        "idle",
        "jump",
        "sit",
        "emote",
        "run",
        "combat_idle",
        "backslash",
        "halfslash"
      ]
    },
    {
      "itemId": "torso_clothes_longsleeve2_cardigan",
      "name": "Cardigan (green)",
      "variant": "",
      "recolors": {
        "clothes": "green"
      },
      "zPos": 35,
      "layerNum": 1,
      "yPos": 0,
      "isCustom": false,
      "needsRecolor": false,
      "fileName": "torso/clothes/longsleeve/longsleeve2_cardigan/male/spellcast.png",
      "supportedAnimations": [
        "spellcast",
        "thrust",
        "walk",
        "slash",
        "shoot",
        "hurt",
        "climb",
        "idle",
        "jump",
        "sit",
        "emote",
        "run",
        "combat_idle",
        "backslash",
        "halfslash"
      ]
    },
    {
      "itemId": "torso_jacket_frock_collar",
      "name": "Frock collar (gold)",
      "variant": "gold",
      "recolors": null,
      "zPos": 57,
      "layerNum": 1,
      "yPos": 0,
      "isCustom": false,
      "needsRecolor": false,
      "fileName": "torso/jacket/trim/frock_collar/spellcast/gold.png",
      "supportedAnimations": [
        "spellcast",
        "thrust",
        "walk",
        "slash",
        "shoot",
        "hurt"
      ]
    },
    {
      "itemId": "heads_human_male",
      "name": "Human Male (olive)",
      "variant": "",
      "recolors": {
        "head": "olive"
      },
      "zPos": 100,
      "layerNum": 1,
      "yPos": 0,
      "isCustom": false,
      "needsRecolor": false,
      "fileName": "head/heads/human/male/spellcast.png",
      "supportedAnimations": [
        "spellcast",
        "thrust",
        "walk",
        "slash",
        "shoot",
        "hurt",
        "climb",
        "idle",
        "jump",
        "sit",
        "emote",
        "run",
        "combat_idle",
        "backslash",
        "halfslash"
      ]
    },
    {
      "itemId": "face_neutral",
      "name": "Neutral (olive)",
      "variant": "",
      "recolors": {
        "expression": "olive"
      },
      "zPos": 101,
      "layerNum": 1,
      "yPos": 0,
      "isCustom": false,
      "needsRecolor": false,
      "fileName": "head/faces/male/neutral/spellcast.png",
      "supportedAnimations": [
        "spellcast",
        "thrust",
        "walk",
        "slash",
        "shoot",
        "idle",
        "jump",
        "sit",
        "emote",
        "run",
        "combat_idle",
        "backslash",
        "halfslash"
      ]
    },
    {
      "itemId": "hair_afro",
      "name": "Afro (light brown)",
      "variant": "light brown",
      "recolors": null,
      "zPos": 120,
      "layerNum": 1,
      "yPos": 0,
      "isCustom": false,
      "needsRecolor": false,
      "fileName": "hair/afro/adult/spellcast/light_brown.png",
      "supportedAnimations": [
        "spellcast",
        "thrust",
        "walk",
        "slash",
        "shoot",
        "hurt",
        "climb",
        "idle",
        "jump",
        "sit",
        "emote",
        "run",
        "combat_idle",
        "backslash",
        "halfslash"
      ]
    }
  ],
  "credits": [
    {
      "fileName": "body/bodies/male/idle.png",
      "file": "body/bodies/male",
      "notes": "see details at https://opengameart.org/content/lpc-character-bases; 'Thick' Male Revised Run/Climb by JaidynReiman (based on ElizaWy's LPC Revised)",
      "authors": [
        "bluecarrot16",
        "JaidynReiman",
        "Benjamin K. Smith (BenCreating)",
        "Evert",
        "Eliza Wyatt (ElizaWy)",
        "TheraHedwig",
        "MuffinElZangano",
        "Durrani",
        "Johannes Sjölund (wulax)",
        "Stephen Challener (Redshrike)"
      ],
      "licenses": [
        "OGA-BY 3.0",
        "CC-BY-SA 3.0",
        "GPL 3.0"
      ],
      "urls": [
        "https://opengameart.org/content/liberated-pixel-cup-lpc-base-assets-sprites-map-tiles",
        "https://opengameart.org/content/lpc-medieval-fantasy-character-sprites",
        "https://opengameart.org/content/lpc-male-jumping-animation-by-durrani",
        "https://opengameart.org/content/lpc-runcycle-and-diagonal-walkcycle",
        "https://opengameart.org/content/lpc-revised-character-basics",
        "https://opengameart.org/content/lpc-be-seated",
        "https://opengameart.org/content/lpc-runcycle-for-male-muscular-and-pregnant-character-bases-with-modular-heads",
        "https://opengameart.org/content/lpc-jump-expanded",
        "https://opengameart.org/content/lpc-character-bases"
      ]
    },
    {
      "fileName": "head/heads/human/male/idle.png",
      "file": "head/heads/human/male",
      "notes": "original head by Redshrike, tweaks by BenCreating, modular version by bluecarrot16",
      "authors": [
        "bluecarrot16",
        "Benjamin K. Smith (BenCreating)",
        "Stephen Challener (Redshrike)"
      ],
      "licenses": [
        "OGA-BY 3.0",
        "CC-BY-SA 3.0",
        "GPL 3.0"
      ],
      "urls": [
        "https://opengameart.org/content/liberated-pixel-cup-lpc-base-assets-sprites-map-tiles",
        "https://opengameart.org/content/lpc-character-bases"
      ]
    },
    {
      "fileName": "head/faces/male/neutral/idle.png",
      "file": "head/faces",
      "notes": "Original by Redshrike, Expressions by ElizaWy, mapped to all frames by JaidynReiman",
      "authors": [
        "JaidynReiman",
        "ElizaWy",
        "Stephen Challener (Redshrike)"
      ],
      "licenses": [
        "OGA-BY 3.0"
      ],
      "urls": [
        "https://github.com/ElizaWy/LPC/tree/main/Characters/Head",
        "https://opengameart.org/content/ulpc-expanded-expressions"
      ]
    },
    {
      "fileName": "hair/afro/adult/idle/light_brown.png",
      "file": "hair/afro",
      "notes": "",
      "authors": [
        "bluecarrot16"
      ],
      "licenses": [
        "CC0"
      ],
      "urls": [
        "https://opengameart.org/content/lpc-hair"
      ]
    },
    {
      "fileName": "torso/jacket/trim/frock_collar/idle/gold.png",
      "file": "torso/jacket/trim",
      "notes": "",
      "authors": [
        "bluecarrot16"
      ],
      "licenses": [
        "OGA-BY 3.0"
      ],
      "urls": [
        "https://opengameart.org/content/lpc-pirates"
      ]
    },
    {
      "fileName": "torso/clothes/longsleeve/longsleeve2_cardigan/male/idle.png",
      "file": "torso/clothes/longsleeve/longsleeve2_cardigan",
      "notes": "original by ElizaWy; spellcast/thrust/shoot/hurt/male adapted from original by JaidynReiman",
      "authors": [
        "ElizaWy",
        "JaidynReiman",
        "Stephen Challener (Redshrike)",
        "Johannes Sjölund (wulax)"
      ],
      "licenses": [
        "OGA-BY 3.0"
      ],
      "urls": [
        "http://opengameart.org/content/lpc-revised-character-basics",
        "https://github.com/ElizaWy/LPC/tree/main/Characters/Clothing",
        "https://opengameart.org/content/lpc-expanded-sit-run-jump-more",
        "https://opengameart.org/content/lpc-expanded-simple-shirts"
      ]
    },
    {
      "fileName": "legs/pantaloons/male/idle.png",
      "file": "legs/pantaloons",
      "notes": "Original bases by Redshrike, thrust/shoot bases by Wulax, Original Pantaloons by Nila122, climb/jump/run/sit/emotes/revised combat by JaidynReiman",
      "authors": [
        "Nila122",
        "JaidynReiman",
        "Johannes Sjölund (wulax)",
        "Stephen Challener (Redshrike)"
      ],
      "licenses": [
        "OGA-BY 3.0",
        "GPL 2.0",
        "GPL 3.0",
        "CC-BY-SA 3.0"
      ],
      "urls": [
        "https://opengameart.org/content/lpc-pirates",
        "https://opengameart.org/content/more-lpc-clothes-and-hair",
        "https://opengameart.org/content/lpc-expanded-pants"
      ]
    },
    {
      "fileName": "feet/sandals/male/idle/yellow.png",
      "file": "feet/sandals",
      "notes": "edited for v3 bases by bluecarrot16, Jump/Sit/Emote/Run/Revised Combat by JaidynReiman",
      "authors": [
        "Nila122",
        "JaidynReiman",
        "Matthew Krohn (makrohn)",
        "Johannes Sjölund (wulax)"
      ],
      "licenses": [
        "OGA-BY 3.0",
        "CC-BY-SA 3.0",
        "GPL 2.0",
        "GPL 3.0"
      ],
      "urls": [
        "https://opengameart.org/content/lpc-roman-armor",
        "http://opengameart.org/content/lpc-clothing-updates",
        "https://opengameart.org/content/lpc-expanded-socks-shoes"
      ]
    }
  ]
}